neaty/__init__.py
neaty/_meta.py
neaty/log.py
neaty/neaty.py
neaty/py.typed
neaty-0.2.0.dist-info/LICENSE.md
neaty-0.2.0.dist-info/METADATA
neaty-0.2.0.dist-info/WHEEL
neaty-0.2.0.dist-info/top_level.txt
neaty-0.2.0.dist-info/RECORD
